Metadata-Version: 1.0
Name: akm-distributions
Version: 0.1
Summary: Probability distributions
Home-page: UNKNOWN
Author: Akhil Kumar Mengani
Author-email: UNKNOWN
License: UNKNOWN
Platform: UNKNOWN
